instantgrade/__init__.py
instantgrade/core/assignment_loader.py
instantgrade/core/models.py
instantgrade/core/orchestrator.py
instantgrade/core/registry.py
instantgrade/core/sandbox_policies.py
instantgrade/evaluators/excel/eval_runner.py
instantgrade/evaluators/excel/evaluator.py
instantgrade/evaluators/excel/excel_executor.py
instantgrade/evaluators/python/__init__.py
instantgrade/evaluators/python/docker_sandbox.py
instantgrade/evaluators/python/evaluator.py
instantgrade/evaluators/python/execution_service.py
instantgrade/evaluators/python/execution_service_docker.py
instantgrade/evaluators/python/notebook_executor.py
instantgrade/evaluators/python/comparison/__init__.py
instantgrade/evaluators/python/comparison/comparison_service.py
instantgrade/evaluators/python/execution/__init__.py
instantgrade/evaluators/python/execution/resources/__init__.py
instantgrade/evaluators/python/execution/resources/grader.py
instantgrade/evaluators/python/ingestion/solution_ingestion.py
instantgrade/reporting/reporting_service.py
instantgrade/utils/io_utils.py
instantgrade/utils/logger.py
instantgrade-0.1.15.dist-info/licenses/LICENSE.txt
instantgrade-0.1.15.dist-info/METADATA
instantgrade-0.1.15.dist-info/WHEEL
instantgrade-0.1.15.dist-info/entry_points.txt
instantgrade-0.1.15.dist-info/top_level.txt
instantgrade-0.1.15.dist-info/RECORD
