Metadata-Version: 2.4
Name: instantgrade
Version: 0.1.15
Summary: An automated evaluation framework for Python notebooks and Excel assignments
Home-page: https://github.com/chandraveshchaudhari/instantgrade
Author: Chandravesh Chaudhari
Author-email: Chandravesh Chaudhari <chandraveshchaudhari@gmail.com>
Maintainer-email: Chandravesh Chaudhari <chandraveshchaudhari@gmail.com>
License: MIT
Project-URL: Homepage, https://github.com/chandraveshchaudhari/instantgrade
Project-URL: Documentation, https://github.com/chandraveshchaudhari/instantgrade/wiki
Project-URL: Repository, https://github.com/chandraveshchaudhari/instantgrade
Project-URL: Bug Tracker, https://github.com/chandraveshchaudhari/instantgrade/issues
Project-URL: Changelog, https://github.com/chandraveshchaudhari/instantgrade/releases
Keywords: evaluation,grading,jupyter,notebook,excel,education,automated-grading,assignment-evaluation,instant,instantgrade
Classifier: Development Status :: 3 - Alpha
Classifier: Intended Audience :: Developers
Classifier: Intended Audience :: Education
Classifier: Intended Audience :: Science/Research
Classifier: Topic :: Software Development :: Testing
Classifier: Topic :: Education
Classifier: Topic :: Software Development :: Libraries :: Python Modules
Classifier: License :: OSI Approved :: MIT License
Classifier: Operating System :: OS Independent
Classifier: Programming Language :: Python :: 3
Classifier: Programming Language :: Python :: 3.8
Classifier: Programming Language :: Python :: 3.9
Classifier: Programming Language :: Python :: 3.10
Classifier: Programming Language :: Python :: 3.11
Classifier: Programming Language :: Python :: 3.12
Classifier: Programming Language :: Python :: 3 :: Only
Requires-Python: >=3.10, <4
License-File: LICENSE.txt
Requires-Dist: openpyxl>=3.0.0
Requires-Dist: pandas>=1.0.0
Requires-Dist: nbformat>=5.0.0
Requires-Dist: nbclient>=0.5.0
Requires-Dist: click>=7.0
Provides-Extra: xlwings
Requires-Dist: xlwings>=0.24.0; extra == "xlwings"
Provides-Extra: dev
Requires-Dist: pytest>=6.0; extra == "dev"
Requires-Dist: black>=21.0; extra == "dev"
Requires-Dist: flake8>=3.9; extra == "dev"
Requires-Dist: build>=0.7.0; extra == "dev"
Requires-Dist: twine>=3.4.0; extra == "dev"
Provides-Extra: test
Requires-Dist: pytest>=6.0; extra == "test"
Requires-Dist: coverage>=5.5; extra == "test"
Dynamic: author
Dynamic: home-page
Dynamic: license-file
Dynamic: requires-python
